envoy_reader/__init__.py
envoy_reader/envoy_reader.py
tests/__init__.py
tests/conftest.py
tests/test_envoy_reader.py
envoy_reader-0.21.3.dist-info/LICENSE
envoy_reader-0.21.3.dist-info/METADATA
envoy_reader-0.21.3.dist-info/WHEEL
envoy_reader-0.21.3.dist-info/top_level.txt
envoy_reader-0.21.3.dist-info/RECORD
